aquacrop/__init__.py
aquacrop/core.py
aquacrop/data/CP.dat
aquacrop/data/CP.st
"aquacrop/data/CP_EC-EARTH[CP,RCP45,2021-2040]WG.dat"
"aquacrop/data/CP_EC-EARTH[CP,RCP45,2041-2060]WG.dat"
"aquacrop/data/CP_EC-EARTH[CP,RCP45,2041-2060]WG.st"
"aquacrop/data/CP_EC-EARTH[CP,RCP45,2061-2080]WG.dat"
"aquacrop/data/CP_EC-EARTH[CP,RCP85,2021-2040]WG.dat"
"aquacrop/data/CP_EC-EARTH[CP,RCP85,2041-2060]WG.dat"
"aquacrop/data/CP_EC-EARTH[CP,RCP85,2061-2080]WG.dat"
aquacrop/data/MaunaLoaCO2.txt
aquacrop/data/__init__.py
aquacrop/data/brussels_climate.txt
aquacrop/data/brussels_future.txt
aquacrop/data/cambridge_climate.txt
aquacrop/data/champion_climate.txt
aquacrop/data/cordoba_climate.txt
aquacrop/data/hyderabad_climate.txt
aquacrop/data/lincolnshire_climate.txt
aquacrop/data/norfolk_climate.txt
aquacrop/data/north_yorks_climate.txt
aquacrop/data/northumberland_climate.txt
aquacrop/data/paddyrice_hyderabad_matlab.txt
aquacrop/data/paddyrice_hyderabad_windows.OUT
aquacrop/data/potato_matlab.txt
aquacrop/data/potato_windows.OUT
aquacrop/data/suffolk_climate.txt
aquacrop/data/tunis_climate.txt
aquacrop/data/tunis_test_1_SandyLoam_matlab.txt
aquacrop/data/tunis_test_1_SandyLoam_windows.OUT
aquacrop/data/tunis_test_1_matlab.txt
aquacrop/data/tunis_test_1_windows.OUT
aquacrop/data/tunis_test_2_long_matlab.txt
aquacrop/data/tunis_test_2_long_windows.OUT
aquacrop/data/tunis_test_3_30taw_matlab.txt
aquacrop/data/tunis_test_3_30taw_windows.OUT
aquacrop/data/tunis_test_6_matlab.txt
aquacrop/data/tunis_test_6_windows.OUT
aquacrop/data/tunis_wheat_gw15_matlab.txt
aquacrop/data/tunis_wheat_gw15_windows.OUT
aquacrop/data/cmip6_woolpit/CanESM5/CanESM5_historical_1995_2014_52.22057_0.8847.csv
aquacrop/data/cmip6_woolpit/CanESM5/CanESM5_ssp245_2020_2039_52.22057_0.8847.csv
aquacrop/data/cmip6_woolpit/CanESM5/CanESM5_ssp245_2040_2059_52.22057_0.8847.csv
aquacrop/data/cmip6_woolpit/CanESM5/CanESM5_ssp245_2060_2079_52.22057_0.8847.csv
aquacrop-3.0.11.dist-info/LICENSE
aquacrop-3.0.11.dist-info/METADATA
aquacrop-3.0.11.dist-info/WHEEL
aquacrop-3.0.11.dist-info/top_level.txt
aquacrop-3.0.11.dist-info/RECORD
