Metadata-Version: 2.2
Name: aquacrop
Version: 3.0.11
Summary: Soil-Crop-Water model based on AquaCrop-OS.
Home-page: https://github.com/aquacropos/aquacrop
Author: Tim Foster
Author-email: timothy.foster@manchester.ac.uk
Project-URL: Bug Tracker, https://github.com/aquacropos/aquacrop/issues
Keywords: aquacrop,aquacropos,aquacrop-ospy,python
Classifier: Programming Language :: Python :: 3.7
Classifier: Programming Language :: Python :: 3.8
Classifier: Programming Language :: Python :: 3.9
Classifier: Programming Language :: Python :: 3.10
Classifier: License :: OSI Approved :: MIT License
Classifier: Operating System :: MacOS
Classifier: Operating System :: Microsoft
Classifier: Operating System :: POSIX :: Linux
Classifier: Natural Language :: English
Requires-Python: >=3.7
License-File: LICENSE
Requires-Dist: numpy>=1.22.0
Requires-Dist: pandas>=2.0.0
Requires-Dist: tqdm>=4.65.0
Requires-Dist: matplotlib>=1.2.0
Requires-Dist: seaborn>=0.13.0
